[
  {
    "name": "pubg-undetected/pubg-cheat",
    "clone_url": "https://github.com/pubg-undetected/pubg-cheat.git",
    "stars": 289,
    "size": 167
  },
  {
    "name": "wgsxm/PartCrafter",
    "clone_url": "https://github.com/wgsxm/PartCrafter.git",
    "stars": 182,
    "size": 3329
  },
  {
    "name": "guandeh17/Self-Forcing",
    "clone_url": "https://github.com/guandeh17/Self-Forcing.git",
    "stars": 171,
    "size": 700
  },
  {
    "name": "hemanth/paws-on-mcp",
    "clone_url": "https://github.com/hemanth/paws-on-mcp.git",
    "stars": 124,
    "size": 68
  },
  {
    "name": "lucasromerodb/liquid-glass-effect-macos",
    "clone_url": "https://github.com/lucasromerodb/liquid-glass-effect-macos.git",
    "stars": 100,
    "size": 3264
  }
]