[
  {
    "name": "skanger/zifei-panel",
    "clone_url": "https://github.com/skanger/zifei-panel.git",
    "stars": 251,
    "size": 1577
  },
  {
    "name": "PRIME-RL/TTRL",
    "clone_url": "https://github.com/PRIME-RL/TTRL.git",
    "stars": 134,
    "size": 1988
  },
  {
    "name": "Tencent-TDS/KuiklyUI",
    "clone_url": "https://github.com/Tencent-TDS/KuiklyUI.git",
    "stars": 124,
    "size": 2507
  },
  {
    "name": "cogiceo/GPOHound",
    "clone_url": "https://github.com/cogiceo/GPOHound.git",
    "stars": 78,
    "size": 89
  },
  {
    "name": "neatethnicity/fiber",
    "clone_url": "https://github.com/neatethnicity/fiber.git",
    "stars": 43,
    "size": 64
  }
]