[
  {
    "name": "yetone/native-feel-skill",
    "clone_url": "https://github.com/yetone/native-feel-skill.git",
    "stars": 946,
    "size": 79
  },
  {
    "name": "Juwluuu/Subnautica-2-Release",
    "clone_url": "https://github.com/Juwluuu/Subnautica-2-Release.git",
    "stars": 360,
    "size": 62
  },
  {
    "name": "mcjavarp/Manager2026",
    "clone_url": "https://github.com/mcjavarp/Manager2026.git",
    "stars": 356,
    "size": 59
  },
  {
    "name": "jiaoyanming0-bot/OPAutoClicker",
    "clone_url": "https://github.com/jiaoyanming0-bot/OPAutoClicker.git",
    "stars": 355,
    "size": 175
  },
  {
    "name": "DARKHOLEUM/VoidStrap-For-Roblox",
    "clone_url": "https://github.com/DARKHOLEUM/VoidStrap-For-Roblox.git",
    "stars": 354,
    "size": 178
  }
]