[
  {
    "name": "iannuttall/fartscroll-lid",
    "clone_url": "https://github.com/iannuttall/fartscroll-lid.git",
    "stars": 232,
    "size": 1204
  },
  {
    "name": "luis22d/ZeroTrace-Stealer-13-2026",
    "clone_url": "https://github.com/luis22d/ZeroTrace-Stealer-13-2026.git",
    "stars": 173,
    "size": 3545
  },
  {
    "name": "jacobsonnora202/SimpleMenu",
    "clone_url": "https://github.com/jacobsonnora202/SimpleMenu.git",
    "stars": 53,
    "size": 1395
  },
  {
    "name": "rongyaofang/prism-bench",
    "clone_url": "https://github.com/rongyaofang/prism-bench.git",
    "stars": 36,
    "size": 1123
  },
  {
    "name": "vakovalskii/searxng-docker-tavily-adapter",
    "clone_url": "https://github.com/vakovalskii/searxng-docker-tavily-adapter.git",
    "stars": 34,
    "size": 140
  }
]