[
  {
    "name": "chaidiscovery/chai-lab",
    "clone_url": "https://github.com/chaidiscovery/chai-lab.git",
    "stars": 116,
    "size": 1181
  },
  {
    "name": "blotterfyi/velocity",
    "clone_url": "https://github.com/blotterfyi/velocity.git",
    "stars": 33,
    "size": 2409
  },
  {
    "name": "DOGECODER69/Apex-Legends-Maphack",
    "clone_url": "https://github.com/DOGECODER69/Apex-Legends-Maphack.git",
    "stars": 20,
    "size": 1504
  },
  {
    "name": "angel8989/Roblox-Nihon",
    "clone_url": "https://github.com/angel8989/Roblox-Nihon.git",
    "stars": 19,
    "size": 751
  },
  {
    "name": "aaradhaybaral/Cheat-CS2",
    "clone_url": "https://github.com/aaradhaybaral/Cheat-CS2.git",
    "stars": 19,
    "size": 161
  }
]