[
  {
    "name": "imbue-bit/TextGAN-Researcher",
    "clone_url": "https://github.com/imbue-bit/TextGAN-Researcher.git",
    "stars": 19,
    "size": 70
  },
  {
    "name": "glidea/one-balance",
    "clone_url": "https://github.com/glidea/one-balance.git",
    "stars": 15,
    "size": 2640
  },
  {
    "name": "ynsmroztas/jsmap_inspector",
    "clone_url": "https://github.com/ynsmroztas/jsmap_inspector.git",
    "stars": 12,
    "size": 88
  },
  {
    "name": "OpCode28/Furniture-Website",
    "clone_url": "https://github.com/OpCode28/Furniture-Website.git",
    "stars": 9,
    "size": 1527
  },
  {
    "name": "Myzel394/destroyerr",
    "clone_url": "https://github.com/Myzel394/destroyerr.git",
    "stars": 8,
    "size": 135
  }
]