[
  {
    "name": "f/fig4ai",
    "clone_url": "https://github.com/f/fig4ai.git",
    "stars": 101,
    "size": 682
  },
  {
    "name": "PollensAI/Pollens",
    "clone_url": "https://github.com/PollensAI/Pollens.git",
    "stars": 95,
    "size": 689
  },
  {
    "name": "RhysSullivan/sf-crime-heatmap",
    "clone_url": "https://github.com/RhysSullivan/sf-crime-heatmap.git",
    "stars": 30,
    "size": 397
  },
  {
    "name": "ASITHA-MD/ASITHA-BOT",
    "clone_url": "https://github.com/ASITHA-MD/ASITHA-BOT.git",
    "stars": 26,
    "size": 231
  },
  {
    "name": "bravekingzhang/copy-coder",
    "clone_url": "https://github.com/bravekingzhang/copy-coder.git",
    "stars": 11,
    "size": 418
  }
]