[
  {
    "name": "qqrss/qrs",
    "clone_url": "https://github.com/qqrss/qrs.git",
    "stars": 60,
    "size": 791
  },
  {
    "name": "balazik/ComfyUI-PuLID-Flux",
    "clone_url": "https://github.com/balazik/ComfyUI-PuLID-Flux.git",
    "stars": 54,
    "size": 2261
  },
  {
    "name": "NomadicDaddy/htmx-debugger",
    "clone_url": "https://github.com/NomadicDaddy/htmx-debugger.git",
    "stars": 51,
    "size": 161
  },
  {
    "name": "jasonxtn/Argus",
    "clone_url": "https://github.com/jasonxtn/Argus.git",
    "stars": 48,
    "size": 118
  },
  {
    "name": "fenaux/soccer-applications",
    "clone_url": "https://github.com/fenaux/soccer-applications.git",
    "stars": 43,
    "size": 490
  }
]