[
  {
    "name": "dujonwalker/project-nova",
    "clone_url": "https://github.com/dujonwalker/project-nova.git",
    "stars": 95,
    "size": 427
  },
  {
    "name": "badsectorlabs/ludus_adaptix_c2",
    "clone_url": "https://github.com/badsectorlabs/ludus_adaptix_c2.git",
    "stars": 72,
    "size": 82
  },
  {
    "name": "codebyabel/OSSP-KWORTLINUX-Abel",
    "clone_url": "https://github.com/codebyabel/OSSP-KWORTLINUX-Abel.git",
    "stars": 70,
    "size": 1943
  },
  {
    "name": "alazaralebel/Knoppix-Os-installation",
    "clone_url": "https://github.com/alazaralebel/Knoppix-Os-installation.git",
    "stars": 68,
    "size": 2207
  },
  {
    "name": "mahlet-em/OSSP_Project_Mahlet-Nigussie",
    "clone_url": "https://github.com/mahlet-em/OSSP_Project_Mahlet-Nigussie.git",
    "stars": 68,
    "size": 4148
  }
]