[
  {
    "name": "tokenizer-decode/email-sleuth",
    "clone_url": "https://github.com/tokenizer-decode/email-sleuth.git",
    "stars": 100,
    "size": 60
  },
  {
    "name": "CJackHwang/AIstudioProxyAPI",
    "clone_url": "https://github.com/CJackHwang/AIstudioProxyAPI.git",
    "stars": 81,
    "size": 3318
  },
  {
    "name": "sergiodxa/react-router-color-scheme-example",
    "clone_url": "https://github.com/sergiodxa/react-router-color-scheme-example.git",
    "stars": 35,
    "size": 62
  },
  {
    "name": "thecybersandeep/Frida-Launcher",
    "clone_url": "https://github.com/thecybersandeep/Frida-Launcher.git",
    "stars": 28,
    "size": 200
  },
  {
    "name": "NaitikJoshiPro/Trading-ZettleKasten",
    "clone_url": "https://github.com/NaitikJoshiPro/Trading-ZettleKasten.git",
    "stars": 21,
    "size": 218
  }
]