[
  {
    "name": "onlineCasinoScript/online-casino-script",
    "clone_url": "https://github.com/onlineCasinoScript/online-casino-script.git",
    "stars": 59,
    "size": 1260
  },
  {
    "name": "mckaywrigley/o1-xml-parser",
    "clone_url": "https://github.com/mckaywrigley/o1-xml-parser.git",
    "stars": 22,
    "size": 193
  },
  {
    "name": "DRukina/HPE-NewOrderRequest",
    "clone_url": "https://github.com/DRukina/HPE-NewOrderRequest.git",
    "stars": 17,
    "size": 925
  },
  {
    "name": "andreia/filament-nord-theme",
    "clone_url": "https://github.com/andreia/filament-nord-theme.git",
    "stars": 17,
    "size": 2380
  },
  {
    "name": "Melanee-Melanee/OCR-on-PDF",
    "clone_url": "https://github.com/Melanee-Melanee/OCR-on-PDF.git",
    "stars": 12,
    "size": 152
  }
]